nvr/__init__.py
nvr/nvr.py
neovim_remote-2.5.1.dist-info/LICENSE
neovim_remote-2.5.1.dist-info/METADATA
neovim_remote-2.5.1.dist-info/WHEEL
neovim_remote-2.5.1.dist-info/entry_points.txt
neovim_remote-2.5.1.dist-info/top_level.txt
neovim_remote-2.5.1.dist-info/RECORD
