Metadata-Version: 2.1
Name: neovim-remote
Version: 2.5.1
Summary: Control nvim processes using "nvr" commandline tool
Home-page: https://github.com/mhinz/neovim-remote
Author: Marco Hinz
Author-email: mh.codebro@gmail.com
License: MIT
Keywords: neovim nvim nvr remote helper
Classifier: Topic :: Utilities
Classifier: License :: OSI Approved :: MIT License
Classifier: Development Status :: 5 - Production/Stable
Classifier: Intended Audience :: End Users/Desktop
Classifier: Intended Audience :: Developers
Classifier: Programming Language :: Python :: 3
Requires-Python: >=3.7
License-File: LICENSE
